{
  "greeting": "Hè looo Zân Anh",
  "name": "(còn thức hong)",
  "greetingText": "Tên dth s1 thế giới kaka!",
  "wishText": "Mong 18 của em trọn vẹn, anh thương em  !!!",
  "imagePath": "img/zanh.jpg",
  "text1": "Nay là cổ đã đượt 18 tuổi, nên là ...",
  "textInChatBox": "Chúc mừng sinh nhật của em, mong là em sẽ đạt được những gì em mong ở tuổi này, và mong em sẽ càng ngày càng xinh hơn nữaaa",
  "sendButtonLabel": "Send",
  "text2": "Khoan",
  "text3": "Tưởng hết ròi ha gì",
  "text4": "Còn một thứ nữa, rất là",
  "text4Adjective": "special",
  "text5Entry": "Bởi vì",
  "text5Content": "Em là người Special nhất đối zới anh",
  "smiley": ":)",
  "bigTextPart1": "S",
  "bigTextPart2": "O",
  "wishHeading": "Happy Birthday!",
  "outroText": "Okay, giờ thì nhắn tin cho anh khang liền đi ảnh chờ kìa",
  "replayText": "Hay bấm vô dòng này, cho coi lại nè hihi", 
  "outroSmiley": ":)"
}
